Metadata-Version: 2.1
Name: nicagemap
Version: 0.0.1
Summary: A python package for interactive mapping
Home-page: https://github.com/OscarVel21/nicagemap
Author: Oscar Santiago Velasquez Muñoz
Author-email: oscar_velasquez1995@hotmail.com
License: MIT license
Keywords: nicagemap
Platform: UNKNOWN
Classifier: Development Status :: 2 - Pre-Alpha
Classifier: Intended Audience :: Developers
Classifier: License :: OSI Approved :: MIT License
Classifier: Natural Language :: English
Classifier: Programming Language :: Python :: 3
Classifier: Programming Language :: Python :: 3.5
Classifier: Programming Language :: Python :: 3.6
Classifier: Programming Language :: Python :: 3.7
Classifier: Programming Language :: Python :: 3.8
Requires-Python: >=3.5
License-File: LICENSE
